vcdatatools/__init__.py
vcdatatools/affinity.py
vcdatatools/airtable.py
vcdatatools/aumni.py
vcdatatools/carta.py
vcdatatools-0.0.2.dist-info/METADATA
vcdatatools-0.0.2.dist-info/WHEEL
vcdatatools-0.0.2.dist-info/top_level.txt
vcdatatools-0.0.2.dist-info/RECORD
