Metadata-Version: 2.1
Name: vcdatatools
Version: 0.0.2
Summary: Methods to manipulate and analyze data from platforms frequently used in venture capital.
Home-page: UNKNOWN
Author: Andrew Yu
Author-email: <hello@yudrew.com>
License: UNKNOWN
Keywords: venture capital,affinity,airtable,aumni,carta,data analysis
Platform: UNKNOWN
Classifier: Development Status :: 3 - Alpha
Classifier: Intended Audience :: Education
Classifier: Programming Language :: Python :: 2
Classifier: Programming Language :: Python :: 3
Classifier: Operating System :: MacOS :: MacOS X
Classifier: Operating System :: Microsoft :: Windows
Requires-Dist: pandas
